dcoscli/__init__.py
dcoscli/log.py
dcoscli/main.py
dcoscli/metrics.py
dcoscli/subcommand.py
dcoscli/tables.py
dcoscli/util.py
dcoscli/auth/__init__.py
dcoscli/auth/main.py
dcoscli/cluster/__init__.py
dcoscli/cluster/main.py
dcoscli/config/__init__.py
dcoscli/config/main.py
dcoscli/data/help/auth.txt
dcoscli/data/help/cluster.txt
dcoscli/data/help/cluster_ee.txt
dcoscli/data/help/config.txt
dcoscli/data/help/dcos.txt
dcoscli/data/help/help.txt
dcoscli/data/help/job.txt
dcoscli/data/help/marathon.txt
dcoscli/data/help/node.txt
dcoscli/data/help/package.txt
dcoscli/data/help/service.txt
dcoscli/data/help/task.txt
dcoscli/data/help/task_exec.txt
dcoscli/help/__init__.py
dcoscli/help/main.py
dcoscli/job/__init__.py
dcoscli/job/main.py
dcoscli/marathon/__init__.py
dcoscli/marathon/main.py
dcoscli/node/__init__.py
dcoscli/node/main.py
dcoscli/package/__init__.py
dcoscli/package/main.py
dcoscli/service/__init__.py
dcoscli/service/main.py
dcoscli/task/__init__.py
dcoscli/task/main.py
dcoscli/test/__init__.py
dcoscli/test/common.py
dcoscli/test/constants.py
dcoscli/test/job.py
dcoscli/test/marathon.py
dcoscli/test/package.py
dcoscli/test/service.py
dcoscli-0.6.1.dist-info/METADATA
dcoscli-0.6.1.dist-info/RECORD
dcoscli-0.6.1.dist-info/WHEEL
dcoscli-0.6.1.dist-info/entry_points.txt
dcoscli-0.6.1.dist-info/top_level.txt
tests/fixtures/__init__.py
tests/fixtures/auth_provider.py
tests/fixtures/clusters.py
tests/fixtures/marathon.py
tests/fixtures/metrics.py
tests/fixtures/metronome.py
tests/fixtures/node.py
tests/fixtures/package.py
tests/fixtures/service.py
tests/fixtures/task.py
tests/integrations/__init__.py
tests/integrations/test_auth.py
tests/integrations/test_cluster.py
tests/integrations/test_cluster_migration.py
tests/integrations/test_config.py
tests/integrations/test_dcos.py
tests/integrations/test_help.py
tests/integrations/test_job.py
tests/integrations/test_marathon.py
tests/integrations/test_marathon_debug.py
tests/integrations/test_marathon_groups.py
tests/integrations/test_marathon_pod.py
tests/integrations/test_node.py
tests/integrations/test_package.py
